partial_tagger/__about__.py
partial_tagger/__init__.py
partial_tagger/matchers.py
partial_tagger/metric.py
partial_tagger/py.typed
partial_tagger/recognizer.py
partial_tagger/tagger.py
partial_tagger/training.py
partial_tagger/utils.py
partial_tagger/crf/__init__.py
partial_tagger/crf/functional.py
partial_tagger/crf/nn.py
partial_tagger/data/__init__.py
partial_tagger/data/collators.py
partial_tagger/encoders/__init__.py
partial_tagger/encoders/base.py
partial_tagger/encoders/transformer.py
pytorch_partial_tagger-0.1.18.dist-info/METADATA
pytorch_partial_tagger-0.1.18.dist-info/WHEEL
pytorch_partial_tagger-0.1.18.dist-info/licenses/LICENSE
pytorch_partial_tagger-0.1.18.dist-info/RECORD
