Metadata-Version: 2.1
Name: pytorch-partial-tagger
Version: 0.1.18
Summary: Sequence Tagger for Partially Annotated Dataset in PyTorch
Project-URL: Homepage, https://github.com/yasufumy/pytorch-partial-tagger
Author-email: Yasufumi Taniguchi <yasufumi.taniguchi@gmail.com>
License: MIT
License-File: LICENSE
Classifier: Programming Language :: Python
Classifier: Programming Language :: Python :: 3.8
Classifier: Programming Language :: Python :: 3.9
Classifier: Programming Language :: Python :: 3.10
Classifier: Programming Language :: Python :: 3.11
Requires-Python: <3.12,>=3.8
Requires-Dist: sequence-classifier>=0.1.3
Requires-Dist: sequence-label>=0.1.4
Requires-Dist: spacy>=3.5.3
Requires-Dist: torch>=2.0.1
Requires-Dist: transformers>=4.29.2
Provides-Extra: dev
Requires-Dist: black>=23.3.0; extra == 'dev'
Requires-Dist: hypothesis>=6.88.1; extra == 'dev'
Requires-Dist: mypy>=1.7.0; extra == 'dev'
Requires-Dist: pytest-cov>=4.1.0; extra == 'dev'
Requires-Dist: pytest>=7.3.1; extra == 'dev'
Requires-Dist: ruff>=0.0.270; extra == 'dev'
Provides-Extra: docs
Requires-Dist: myst-parser>=2.0.0; extra == 'docs'
Requires-Dist: sphinx-book-theme>=1.0.1; extra == 'docs'
Requires-Dist: sphinx-copybutton>=0.5.2; extra == 'docs'
Requires-Dist: sphinx>=6.2.1; extra == 'docs'
